{
  "main": {
    "id": "d7a3b218431fe5d6",
    "type": "split",
    "children": [
      {
        "id": "da22538a389aedc6",
        "type": "tabs",
        "dimension": 66.01876675603218,
        "children": [
          {
            "id": "a2e6a822f9902853",
            "type": "leaf",
            "state": {
              "type": "markdown",
              "state": {
                "file": "The Fall and Rise of Gather/4. The Fourth Gathering/Woodworking.md",
                "mode": "source",
                "source": false
              }
            }
          },
          {
            "id": "9b638acffab009cb",
            "type": "leaf",
            "state": {
              "type": "markdown",
              "state": {
                "file": "The Fall and Rise of Gather/5. The Fifth Gathering/Try, try again.md",
                "mode": "source",
                "source": false
              }
            }
          },
          {
            "id": "ca401ecacb049379",
            "type": "leaf",
            "state": {
              "type": "markdown",
              "state": {
                "file": "The Fall and Rise of Gather/6. The Sixth Gathering/War Never Fails.md",
                "mode": "source",
                "source": false
              }
            }
          },
          {
            "id": "0648a9598f52ad36",
            "type": "leaf",
            "state": {
              "type": "markdown",
              "state": {
                "file": "The Fall and Rise of Gather/4. The Fourth Gathering/4. The Fourth Gathering.md",
                "mode": "source",
                "source": false
              }
            }
          },
          {
            "id": "2e1b0b4ca0371ea8",
            "type": "leaf",
            "state": {
              "type": "markdown",
              "state": {
                "file": "Markdown Cheat Sheet.md",
                "mode": "source",
                "source": false
              }
            }
          },
          {
            "id": "daaf99b6afebf0b7",
            "type": "leaf",
            "state": {
              "type": "markdown",
              "state": {
                "file": "The Fall and Rise of Gather/5. The Fifth Gathering/Tainted Love.md",
                "mode": "source",
                "source": false
              }
            }
          }
        ],
        "currentTab": 4
      },
      {
        "id": "3dacbf1e21118ac3",
        "type": "split",
        "dimension": 33.98123324396783,
        "children": [
          {
            "id": "2f6bec5100ca5e4b",
            "type": "tabs",
            "dimension": 59.43627450980392,
            "children": [
              {
                "id": "eb1598e945b9ff4b",
                "type": "leaf",
                "state": {
                  "type": "markdown",
                  "state": {
                    "file": "The Fall and Rise of Gather/Information/Naming Conventions.md",
                    "mode": "source",
                    "source": false
                  }
                }
              },
              {
                "id": "78d498b0fc61bdc0",
                "type": "leaf",
                "state": {
                  "type": "markdown",
                  "state": {
                    "file": "The Fall and Rise of Gather/7. The Seventh Gathering/7. The Seventh Gathering.md",
                    "mode": "source",
                    "source": false
                  }
                }
              },
              {
                "id": "c1e1279b8d9d3412",
                "type": "leaf",
                "state": {
                  "type": "markdown",
                  "state": {
                    "file": "The Fall and Rise of Gather/4. The Fourth Gathering/Notable Characters 4.md",
                    "mode": "source",
                    "source": false
                  }
                }
              },
              {
                "id": "8bb20051b9d77e1a",
                "type": "leaf",
                "state": {
                  "type": "markdown",
                  "state": {
                    "file": "The Fall and Rise of Gather/5. The Fifth Gathering/5. The Fifth Gathering.md",
                    "mode": "source",
                    "source": false
                  }
                }
              },
              {
                "id": "f4e15364cf66c398",
                "type": "leaf",
                "state": {
                  "type": "markdown",
                  "state": {
                    "file": "The Fall and Rise of Gather/7. The Seventh Gathering/7. The Seventh Gathering.md",
                    "mode": "source",
                    "source": false
                  }
                }
              }
            ],
            "currentTab": 3
          },
          {
            "id": "d1cbebeedd6c8568",
            "type": "tabs",
            "dimension": 40.56372549019608,
            "children": [
              {
                "id": "96cc07eb0241face",
                "type": "leaf",
                "pinned": true,
                "state": {
                  "type": "graph",
                  "state": {},
                  "pinned": true
                }
              }
            ]
          }
        ],
        "direction": "horizontal"
      }
    ],
    "direction": "vertical"
  },
  "left": {
    "id": "d8c21d283608f134",
    "type": "split",
    "children": [
      {
        "id": "4d22c90a1fbdc9d8",
        "type": "tabs",
        "children": [
          {
            "id": "502f692d6c89d690",
            "type": "leaf",
            "state": {
              "type": "file-explorer",
              "state": {
                "sortOrder": "alphabetical"
              }
            }
          },
          {
            "id": "d431aec6b78eee93",
            "type": "leaf",
            "state": {
              "type": "search",
              "state": {
                "query": "",
                "matchingCase": false,
                "explainSearch": false,
                "collapseAll": false,
                "extraContext": false,
                "sortOrder": "alphabetical"
              }
            }
          },
          {
            "id": "9271dec1ba2e51d6",
            "type": "leaf",
            "state": {
              "type": "bookmarks",
              "state": {}
            }
          },
          {
            "id": "2f2f1a0936cca18f",
            "type": "leaf",
            "state": {
              "type": "VIEW_TYPE_LONGFORM_EXPLORER",
              "state": {}
            }
          }
        ],
        "currentTab": 1
      }
    ],
    "direction": "horizontal",
    "width": 300
  },
  "right": {
    "id": "95e6cd6d8d4f9916",
    "type": "split",
    "children": [
      {
        "id": "cd509c68b02093fc",
        "type": "tabs",
        "children": [
          {
            "id": "a4f9007d817820cf",
            "type": "leaf",
            "state": {
              "type": "backlink",
              "state": {
                "file": "Markdown Cheat Sheet.md",
                "collapseAll": false,
                "extraContext": false,
                "sortOrder": "alphabetical",
                "showSearch": false,
                "searchQuery": "",
                "backlinkCollapsed": false,
                "unlinkedCollapsed": true
              }
            }
          },
          {
            "id": "ec4d7757a75f30ca",
            "type": "leaf",
            "state": {
              "type": "outgoing-link",
              "state": {
                "file": "Markdown Cheat Sheet.md",
                "linksCollapsed": false,
                "unlinkedCollapsed": true
              }
            }
          },
          {
            "id": "197c82391c91ca24",
            "type": "leaf",
            "state": {
              "type": "tag",
              "state": {
                "sortOrder": "frequency",
                "useHierarchy": true
              }
            }
          },
          {
            "id": "da641d67723d948c",
            "type": "leaf",
            "state": {
              "type": "outline",
              "state": {
                "file": "Markdown Cheat Sheet.md"
              }
            }
          },
          {
            "id": "5c003a23a9bc2665",
            "type": "leaf",
            "state": {
              "type": "juggl_nodes",
              "state": {}
            }
          },
          {
            "id": "8a63726b3fb99150",
            "type": "leaf",
            "state": {
              "type": "juggl_style",
              "state": {}
            }
          },
          {
            "id": "9806703a13b884c0",
            "type": "leaf",
            "state": {
              "type": "all-properties",
              "state": {
                "sortOrder": "frequency",
                "showSearch": false,
                "searchQuery": ""
              }
            }
          }
        ]
      }
    ],
    "direction": "horizontal",
    "width": 300,
    "collapsed": true
  },
  "left-ribbon": {
    "hiddenItems": {
      "graph:Open graph view": false,
      "switcher:Open quick switcher": false,
      "canvas:Create new canvas": true,
      "daily-notes:Open today's daily note": true,
      "templates:Insert template": false,
      "command-palette:Open command palette": false,
      "obsidian-wordnet-plugin:WordNet Dictionary": false,
      "3d-graph:3D Graph": false,
      "dangerzone-writing-plugin:Dangerzone Writing": false,
      "juggl:Juggl global graph": false,
      "table-editor-obsidian:Advanced Tables Toolbar": false,
      "obsidian-wordy:Wordy view": false,
      "publish:Publish changes...": false
    }
  },
  "floating": {
    "id": "4ef0ad64f9957c0a",
    "type": "floating",
    "children": [
      {
        "id": "0acfc416b88a8a27",
        "type": "window",
        "children": [
          {
            "id": "f142f82dc1707b04",
            "type": "tabs",
            "dimension": 31.93916349809886,
            "children": [
              {
                "id": "f4f975678262d2f2",
                "type": "leaf",
                "pinned": true,
                "state": {
                  "type": "markdown",
                  "state": {
                    "file": "The Fall and Rise of Gather/Information/Crèches.md",
                    "mode": "source",
                    "source": false
                  },
                  "pinned": true
                }
              }
            ]
          },
          {
            "id": "d3e876600a5b3e48",
            "type": "tabs",
            "dimension": 31.93916349809886,
            "children": [
              {
                "id": "ff6eb261cf67794a",
                "type": "leaf",
                "state": {
                  "type": "markdown",
                  "state": {
                    "file": "The Fall and Rise of Gather/Information/Naming Conventions.md",
                    "mode": "source",
                    "source": false
                  }
                }
              }
            ]
          },
          {
            "id": "7dd379fad55ca12e",
            "type": "tabs",
            "dimension": 36.12167300380228,
            "children": [
              {
                "id": "03efc88778c8498c",
                "type": "leaf",
                "state": {
                  "type": "markdown",
                  "state": {
                    "file": "The Fall and Rise of Gather/Information/Species.md",
                    "mode": "source",
                    "source": false
                  }
                }
              }
            ]
          }
        ],
        "direction": "vertical",
        "x": 3531,
        "y": 16,
        "width": 600,
        "height": 631,
        "maximize": true,
        "zoom": -0.5
      }
    ]
  },
  "active": "2e1b0b4ca0371ea8",
  "lastOpenFiles": [
    "The Fall and Rise of Gather/5. The Fifth Gathering/Tainted Love.md",
    "The Fall and Rise of Gather/Information/Naming Conventions.md",
    "The Fall and Rise of Gather/Information/Crèches.md",
    "Markdown Cheat Sheet.md",
    "The Fall and Rise of Gather/5. The Fifth Gathering/5. The Fifth Gathering.md",
    "The Fall and Rise of Gather/Information/Species.md",
    "The Fall and Rise of Gather/Information/Vocabulary and Style Guide.md",
    "The Fall and Rise of Gather/5. The Fifth Gathering/Spider.png",
    "The Fall and Rise of Gather/5. The Fifth Gathering/Let Loose.md",
    "The Fall and Rise of Gather/5. The Fifth Gathering/The Monks of Madness.md",
    "The Fall and Rise of Gather/5. The Fifth Gathering/Try, try again.md",
    "The Fall and Rise of Gather/5. The Fifth Gathering/Tranquility 4.md",
    "The Fall and Rise of Gather/5. The Fifth Gathering/Sepsis.md",
    "The Fall and Rise of Gather/5. The Fifth Gathering/Eternity in a Day.md",
    "The Fall and Rise of Gather/4. The Fourth Gathering/Woodworking.md",
    "The Fall and Rise of Gather/4. The Fourth Gathering/The Worst of All Possible Worlds.md",
    "The Fall and Rise of Gather/4. The Fourth Gathering/The Tale of Lauren.md",
    "The Fall and Rise of Gather/5. The Fifth Gathering/Capital Planets 5.md",
    "The Fall and Rise of Gather/4. The Fourth Gathering/4. The Fourth Gathering.md",
    "The Fourth Gathering.md",
    "readme.md",
    "The Fall and Rise of Gather/2. The Second Gathering/Depths of Insanity.md",
    "The Fall and Rise of Gather/2. The Second Gathering/Let's Just Leave it at That.md",
    "The Fall and Rise of Gather/4. The Fourth Gathering/Shifting.md",
    "The Fall and Rise of Gather/Information/Notable Characters.md",
    "The Fall and Rise of Gather/2. The Second Gathering/Vivisection of a Disaster.md",
    "The Fall and Rise of Gather/6. The Sixth Gathering/War Never Fails.md",
    "The Fall and Rise of Gather/Images/Spider.png",
    "The Fall and Rise of Gather/Images/Doorknob.png",
    "The Fall and Rise of Gather/2. The Second Gathering/Untitled",
    "The Fall and Rise of Gather/Images",
    "The Fall and Rise of Gather/Gather.canvas"
  ]
}